<?xml version="1.0" encoding="utf-8"?>
<Layout width="640" height="480" keepAspectRatio="true">


    <!-- ***************************************************************************** 
    
        Layout for UI elements:
            * Most of the values are expressed in pixels.
            * All UI elements have a Z-Index (draw order) starting from 100.
            * Dimmens depends of the orientation (whatever is vertical or not) of the element
                * Vertical: 
                    - "dimmen" is treated as "width"
                    - "invdimmen" is treated as "height"
                * Horizontal: 
                    - "dimmen" is treated as "height"
                    - "invdimmen" is treated as "width"
            * "strum_count" indicates how many strums (not strum lines) are defined on this layout
            * In some placeholders only "width" or "height" is required depending on the orientation
            * RANKINGCOUNTER and STREAKCOUNTER can be overrided by stage layout

        ANY SPRITE, SOUND, VIDEO OR TEXTSPRITE IS IGNORED (NEVER DRAWN IN SCREEN)

    ******************************************************************************* -->


    <!-- ******************* UI COMMON VALUES ******************* -->
    <Font name="ui_font" path="/assets/common/font/vcr.ttf" />
    <AttachValue name="ui_animlist" type="string" value="/assets/common/anims/week-round.xml" />


    <!-- ******************* SONGPROGRESSBAR DEFINITION ******************* -->
	<Placeholder name="ui_songprogressbar" x="200" y="12" z="102" width="240" height="8" alignHorizontal="center" />

	<!-- songprogressbar additional parameters -->
	<AttachValue name="ui_songprogressbar_borderSize" type="float" value="2" />
	<AttachValue name="ui_songprogressbar_fontSize" type="float" value="18" />
	<AttachValue name="ui_songprogressbar_fontBorderSize" type="float" value="2" />
	<AttachValue name="ui_songprogressbar_isVertical" type="boolean" value="false" />
	<AttachValue name="ui_songprogressbar_showTime" type="boolean" value="true" />
	<AttachValue name="ui_songprogressbar_colorRGBA8_text"       type="hex" value="0xFFFFFFFF" />
	<AttachValue name="ui_songprogressbar_colorRGBA8_background" type="hex" value="0x000000FF" />
	<AttachValue name="ui_songprogressbar_colorRGBA8_barBack"    type="hex" value="0x808080FF" />
	<AttachValue name="ui_songprogressbar_colorRGBA8_barFront"   type="hex" value="0xFFFFFFFF" />



    <!-- ******************* STRUMS DEFINITIONS ******************* -->
    <AttachValue name="ui_strums_count" type="integer" value="2" />

    <!-- strums positions on the screen -->
    <Placeholder name="ui_strums0" x="26" y="24" z="101" height="456" />
    <Placeholder name="ui_strums1" x="390" y="24" z="101" height= "456" />

    <!-- strums additional parameters -->
    <AttachValue name="ui_strums_gap0" type="float" value="2" />
    <AttachValue name="ui_strums_keepMarkerScale0" type="boolean" value="true" />
    <AttachValue name="ui_strums_markerDimmen0" type="float" value="54" />
    <AttachValue name="ui_strums_markerInvdimmen0" type="float" value="54" />
    <AttachValue name="ui_strums_sustainAlpha0" type="float" value="0.8" />
    <AttachValue name="ui_strums_verticalScroll0" type="boolean" value="true" />

    <AttachValue name="ui_strums_gap1" type="float" value="2" />
    <AttachValue name="ui_strums_keepMarkerScale1" type="boolean" value="true" />
    <AttachValue name="ui_strums_markerDimmen1" type="float" value="54" />
    <AttachValue name="ui_strums_markerInvdimmen1" type="float" value="54" />
    <AttachValue name="ui_strums_sustainAlpha1" type="float" value="0.8" />
    <AttachValue name="ui_strums_verticalScroll1" type="boolean" value="true" />


    <!-- ******************* HEALTHBAR DEFINITION ******************* -->
    <Placeholder name="ui_healthbar" x="170" y="432" z="100" width="300" height="8" />

    <!-- healthbar additional parameters -->
    <AttachValue name="ui_healthbar_isVertical" type="boolean" value="false" />
    <AttachValue name="ui_healthbar_showWarnings" type="boolean" value="true" />
    <AttachValue name="ui_healthbar_borderSize" type="float" value="2" />
    <AttachValue name="ui_healthbar_iconOverlap" type="float" value="10" />
    <AttachValue name="ui_healthbar_warningHeight" type="float" value="20" />
    <AttachValue name="ui_healthbar_lockedHeight" type="float" value="36" />


    <!-- ******************* ROUNDSTATS DEFINITION ******************* -->
    <Placeholder name="ui_roundstats" x="0" y="462" z="102" />

    <!-- roundstats additional parameters -->
    <AttachValue name="ui_roundstats_hidden" type="boolean" value="false" />
    <AttachValue name="ui_roundstats_fontSize" type="float" value="14" />
    <AttachValue name="ui_roundstats_fontBorderSize" type="float" value="2.5" />
    <AttachValue name="ui_roundstats_fontColor" type="hex" value="0xFFFFFF" />


    <!-- ******************* STREAKCOUNTER DEFINITION ******************* -->
    <Placeholder name="ui_streakcounter" x="270" y="370" z="100" height="36" width="0" />

    <!-- streakcounter additional parameters -->
    <AttachValue name="ui_streakcounter_comboHeight" type="float" value="48" /><!-- To hide use 0 -->
    <AttachValue name="ui_streakcounter_numberGap" type="float" value="0" />
    <AttachValue name="ui_streakcounter_delay" type="float" value="0" />


    <!-- ******************* RANKINGCOUNTER  DEFINITION ******************* -->
    <Placeholder name="ui_rankingcounter_rank" x="300" y="160" z="100" height="48" />
    <Placeholder name="ui_rankingcounter_accuracy" x="400" y="240" z="100" height="20" />

    <!-- rankingcounter additional parameters -->
    <AttachValue name="ui_rankingcounter_accuracy_percent" type="boolean" value="false" />


    <!-- ******************* SONG NAME & DIFFICULTY DEFINITION ******************* -->
    <Placeholder name="ui_song_info" x="5" y="462" z="101" />

    <!-- rankingcounter additional parameters -->
    <AttachValue name="ui_song_info_fontSize" type="float" value="13" />
    <AttachValue name="ui_song_info_fontBorderSize" type="float" value="2.5" />
    <AttachValue name="ui_song_info_fontColor" type="hex" value="0xFFFFFF" />
    
    
    <!-- ******************* INVERTED DEFINITIONS ******************* -->
    <!-- Important: -->
    <!--    if the user enables the "inverted strum scrolling" option in settings menu -->
    <!--    the scroll direction is inverted keeping the declared orientation (vertical or horizontal). -->
    <!--    UI elements that should be moved are: songprogressbar, strums, healthbar, roundstats and songinfo -->
	<!--    For this layout strums are inverted from UPSCROLL to DOWNSCROLL because the orientation is vertical. -->
	<!--    In custom layouts with horizontal scrolling, this changes from RIGHTSCROLL to LEFTSCROLL -->
    <Placeholder name="ui_strums_inverted0" x="26" y="0" z="101" height="456" />
    <Placeholder name="ui_strums_inverted1" x="390" y="0" z="101" height= "456" />
	<Placeholder name="ui_songprogressbar_inverted" x="200" y="458" z="102" width="240" height="8" alignHorizontal="center" />
    <Placeholder name="ui_healthbar_inverted" x="170" y="48" z="100" width="300" height="8" />
    <Placeholder name="ui_roundstats_inverted" x="0" y="14" z="102" />
    <Placeholder name="ui_song_info_inverted" x="5" y="14" z="101" />
	

	<!-- **************************************************************************************************** -->
    <!-- Example of placing characters in the stage layout -->
    <!--                                                                 -->
    <!-- Notes: -->
    <!--   * Characters placed here (ui layout) are ignored by the engine. -->
    <!--   * The name "character_###" indicates the player index in the "gameplaymanifest.json" file. -->
    <!--   * If "alignVertical" or "alignHorizontal" is not present, is assumed as "none" aligned. -->
    <!--   * In "alignVertical" and/or "alignHorizontal" use "none" to use the align from -->
    <!--       the character manifest (json file of the character). -->
    <!--   * If the placeholder as "width" or "height" or both, is taken as reference box. -->
    <!--   * "character_girlfriend_scale" and "character_scale_###" defines the sprite scale (optional, defaults to 1.0) -->

    <!-- <Placeholder name="character_girlfriend" x="1" y="4" z="0" /> -->
    <!-- <AttachValue name="character_girlfriend_scale" type="float" value="1.0" /> -->

    <!-- Count of "character_###" placeholders-->
    <!-- <AttachValue name="character_count" type="integer" value="3" /> -->
    
    <!-- <AttachValue name="character_scale_0" type="float" value="0.5" /> -->

    <!-- <Placeholder name="character_0" x="2" y="3" z="0" width="320" height="240" /> -->
    <!-- <Placeholder name="character_1" x="3" y="2" z="0" alignVertical="none" alignHorizontal="end" /> -->
    <!-- <Placeholder name="character_2" x="4" y="1" z="0" alignVertical="start" alignHorizontal="start" /> -->
    
</Layout>
