{
	"default": {
		"players": [
			{ "controller": -1, "isOpponent": true, "strumsInLayoutId": 0, "manifest": "PICO/PICO.json" },
			{ "controller": 0, "isOpponent": false, "strumsInLayoutId": 1, "manifest": "#boyfriend" }
		],
		"girlfriend": { "manifest": "#girlfriend" },
		"stage": "philly/layout.xml",
		"script": "philly/week3.lua"
	},
	"songs": [
		{ "name": "Pico"},
		{ "name": "Philly Nice", "chart": "charts/philly.json", "file": "songs/philly.ogg" },
		{ "name": "Blammed" }
	]
}

